MANIFEST.in
README.rst
setup.py
docs/HISTORY.txt
docs/LICENSE.GPL
docs/LICENSE.txt
ftw/__init__.py
ftw.downloadtoken.egg-info/PKG-INFO
ftw.downloadtoken.egg-info/SOURCES.txt
ftw.downloadtoken.egg-info/dependency_links.txt
ftw.downloadtoken.egg-info/entry_points.txt
ftw.downloadtoken.egg-info/namespace_packages.txt
ftw.downloadtoken.egg-info/not-zip-safe
ftw.downloadtoken.egg-info/requires.txt
ftw.downloadtoken.egg-info/top_level.txt
ftw/downloadtoken/__init__.py
ftw/downloadtoken/configure.zcml
ftw/downloadtoken/events.py
ftw/downloadtoken/interfaces.py
ftw/downloadtoken/storage.py
ftw/downloadtoken/testing.py
ftw/downloadtoken/browser/__init__.py
ftw/downloadtoken/browser/configure.zcml
ftw/downloadtoken/browser/downloadfile.py
ftw/downloadtoken/browser/mail_downloadtoken.pt
ftw/downloadtoken/browser/sendmail.py
ftw/downloadtoken/journal/__init__.py
ftw/downloadtoken/journal/subscribers.py
ftw/downloadtoken/locales/ftw.downloadtoken.pot
ftw/downloadtoken/locales/de/LC_MESSAGES/ftw.downloadtoken.po
ftw/downloadtoken/locales/en/LC_MESSAGES/ftw.downloadtoken.po
ftw/downloadtoken/profiles/default/actions.xml
ftw/downloadtoken/tests/__init__.py
ftw/downloadtoken/tests/test_download_by_token.py
ftw/downloadtoken/tests/test_send_mail.py
ftw/downloadtoken/tests/test_storage.py