Metadata-Version: 1.1
Name: ftw.downloadtoken
Version: 1.1.0
Summary: Grants temporary access to a specific downloadable content.
Home-page: https://github.com/4teamwork/ftw.downloadtoken
Author: 4teamwork AG
Author-email: mailto:info@4teamwork.ch
License: GPL2
Platform: UNKNOWN
Classifier: Framework :: Plone
Classifier: Framework :: Plone :: 4.1
Classifier: Framework :: Plone :: 4.2
Classifier: Framework :: Plone :: 4.3
Classifier: Programming Language :: Python
Classifier: Topic :: Software Development :: Libraries :: Python Modules
